README.rst
setup.cfg
setup.py
vegas_lattice.egg-info/PKG-INFO
vegas_lattice.egg-info/SOURCES.txt
vegas_lattice.egg-info/dependency_links.txt
vegas_lattice.egg-info/entry_points.txt
vegas_lattice.egg-info/requires.txt
vegas_lattice.egg-info/top_level.txt
vlattice/__init__.py
vlattice/lattice.py
vlattice/material.py
vlattice/scripts.py