Metadata-Version: 1.1
Name: vegas-lattice
Version: 0.4.0
Summary: A grid lattice sample generator
Home-page: https://github.com/odarbelaeze/vegas-lattice
Author: Oscar D. Arbeláez <@odarbelaeze>, Juan D. Alzate <@jdalzatec>
Author-email: odarbelaeze@gmail.com
License: MIT license
Download-URL: https://github.com/odarbelaeze/vegas-lattice/tarball/0.4.0
Keywords: lattice,graph,magnetite,construction,grid
Platform: UNKNOWN
Classifier: Development Status :: 5 - Production/Stable
Classifier: Environment :: Console
Classifier: Intended Audience :: Science/Research
Classifier: License :: OSI Approved :: MIT License
Classifier: Programming Language :: Python :: 3.4
Classifier: Programming Language :: Python :: 3.5
Classifier: Programming Language :: Python :: 3 :: Only
Classifier: Topic :: Scientific/Engineering :: Physics
